finance_calculator_kolya_super/__init__.py
finance_calculator_kolya_super/__main__.py
finance_calculator_kolya_super/calculator.py
finance_calculator_kolya_super-0.1.1.dist-info/METADATA
finance_calculator_kolya_super-0.1.1.dist-info/WHEEL
finance_calculator_kolya_super-0.1.1.dist-info/entry_points.txt
finance_calculator_kolya_super-0.1.1.dist-info/top_level.txt
finance_calculator_kolya_super-0.1.1.dist-info/RECORD
