Metadata-Version: 2.1
Name: finance_calculator_kolya_super
Version: 0.1.1
Summary: Krutoi packege
Author: Nikolai
Author-email: kolaleuhin@gmail.com
